README.rst
setup.py
ppm/__init__.py
ppm/utils.py
ppm/Commands/__init__.py
ppm/Commands/add.py
ppm/Commands/init.py
ppm/Commands/remove.py
ppm/Commands/run.py
ppm/Commands/start.py
pythonpm.egg-info/PKG-INFO
pythonpm.egg-info/SOURCES.txt
pythonpm.egg-info/dependency_links.txt
pythonpm.egg-info/entry_points.txt
pythonpm.egg-info/not-zip-safe
pythonpm.egg-info/requires.txt
pythonpm.egg-info/top_level.txt