Metadata-Version: 1.1
Name: pythonpm
Version: 0.1.2
Summary: The Python Package Manager that make your life easier.
Home-page: https://github.com/luisholanda/ppm
Author: Luis Holanda
Author-email: luiscmholanda@gmail.com
License: MIT
Keywords: easy_install distutils setuptools
Platform: UNKNOWN
Classifier: Intended Audience :: Developers
Classifier: License :: OSI Approved :: MIT License
Classifier: Topic :: Software Development :: Build Tools
Classifier: Programming Language :: Python :: 3
Classifier: Programming Language :: Python :: 3.6
